DatasetsEvaluator/DatasetsEvaluator.py
DatasetsEvaluator/__init__.py
DatasetsEvaluator-0.0.5.dist-info/LICENSE.txt
DatasetsEvaluator-0.0.5.dist-info/METADATA
DatasetsEvaluator-0.0.5.dist-info/WHEEL
DatasetsEvaluator-0.0.5.dist-info/top_level.txt
DatasetsEvaluator-0.0.5.dist-info/RECORD
