Metadata-Version: 2.1
Name: DatasetsEvaluator
Version: 0.0.5
Summary: A tool to automate collecting and testing against datasets on openml.org
Home-page: UNKNOWN
Author: Brett Kennedy
Author-email: wm.brett.kennedy@gmail.com
License: UNKNOWN
Keywords: machine learning classification regression evaulation public datasets
Platform: UNKNOWN
Classifier: Development Status :: 3 - Alpha
Classifier: License :: OSI Approved :: MIT License
Classifier: Programming Language :: Python :: 3
License-File: LICENSE.txt
Requires-Dist: numpy
Requires-Dist: pandas
Requires-Dist: openml
